package com.javatpoint.mypackage;

public class Employee {

    private int id;
    private String firstName;
    private String lastName;

    public Employee() {
        // <editor-fold defaultstate="collapsed" desc="Compiled Code">
        /* 0: aload_0
         * 1: invokespecial java/lang/Object."<init>":()V
         * 4: return
         *  */
        // </editor-fold>
    }

    public int getId() {
        // <editor-fold defaultstate="collapsed" desc="Compiled Code">
        /* 0: aload_0
         * 1: getfield      com/javatpoint/mypackage/Employee.id:I
         * 4: ireturn
         *  */
        // </editor-fold>
    }

    public void setId(int i) {
        // <editor-fold defaultstate="collapsed" desc="Compiled Code">
        /* 0: aload_0
         * 1: iload_1
         * 2: putfield      com/javatpoint/mypackage/Employee.id:I
         * 5: return
         *  */
        // </editor-fold>
    }

    public String getFirstName() {
        // <editor-fold defaultstate="collapsed" desc="Compiled Code">
        /* 0: aload_0
         * 1: getfield      com/javatpoint/mypackage/Employee.firstName:Ljava/lang/String;
         * 4: areturn
         *  */
        // </editor-fold>
    }

    public void setFirstName(String string) {
        // <editor-fold defaultstate="collapsed" desc="Compiled Code">
        /* 0: aload_0
         * 1: aload_1
         * 2: putfield      com/javatpoint/mypackage/Employee.firstName:Ljava/lang/String;
         * 5: return
         *  */
        // </editor-fold>
    }

    public String getLastName() {
        // <editor-fold defaultstate="collapsed" desc="Compiled Code">
        /* 0: aload_0
         * 1: getfield      com/javatpoint/mypackage/Employee.lastName:Ljava/lang/String;
         * 4: areturn
         *  */
        // </editor-fold>
    }

    public void setLastName(String string) {
        // <editor-fold defaultstate="collapsed" desc="Compiled Code">
        /* 0: aload_0
         * 1: aload_1
         * 2: putfield      com/javatpoint/mypackage/Employee.lastName:Ljava/lang/String;
         * 5: return
         *  */
        // </editor-fold>
    }
}
